README.rst
setup.cfg
setup.py
db/__init__.py
db/_db.py
db/connection.py
db/dialect.py
db/errors.py
db/pool.py
db/mysql/__init__.py
db/mysql/connection.py
db/mysql/dialect.py
db/pymysql/__init__.py
db/pymysql/connection.py
db/pymysql/dialect.py
db/query/__init__.py
db/query/base.py
db/query/delete.py
db/query/expr.py
db/query/insert.py
db/query/select.py
db/query/update.py
dbpy.egg-info/PKG-INFO
dbpy.egg-info/SOURCES.txt
dbpy.egg-info/dependency_links.txt
dbpy.egg-info/not-zip-safe
dbpy.egg-info/requires.txt
dbpy.egg-info/top_level.txt