Metadata-Version: 1.1
Name: dbpy
Version: 0.1.2
Summary: database abstraction layer for pythoneer
Home-page: https://github.com/thomashuang/dbpy
Author: Thomas Huang
Author-email: lyanghwy@gmail.com
License: GPL
Keywords: database abstraction layer for pythoneer(orm,database)
Platform: UNKNOWN
Classifier: Development Status :: 3 - Alpha
Classifier: License :: OSI Approved :: GNU Affero General Public License v3
Classifier: Natural Language :: English
Classifier: Programming Language :: Python
Classifier: Programming Language :: Python :: 2.7
Classifier: Operating System :: OS Independent
Classifier: Topic :: Database
